cronut/__init__.py
cronut/app.py
cronut/utils.py
cronut-0.1.0.dist-info/LICENSE
cronut-0.1.0.dist-info/METADATA
cronut-0.1.0.dist-info/WHEEL
cronut-0.1.0.dist-info/top_level.txt
cronut-0.1.0.dist-info/RECORD
