Metadata-Version: 2.1
Name: cronut
Version: 0.1.0
Summary: Tasty event processing with Kafka
Home-page: https://gitlab.com/myNameIsPatrick/cronut
Author: Patrick Godwin
Author-email: patrick.godwin@psu.edu
License: BSD 3-Clause
Platform: UNKNOWN
Classifier: Development Status :: 2 - Pre-Alpha
Classifier: Programming Language :: Python
Classifier: Programming Language :: Python :: 2.7
Classifier: Programming Language :: Python :: 3
Classifier: Intended Audience :: Science/Research
Classifier: Intended Audience :: Developers
Classifier: Natural Language :: English
Classifier: Topic :: Scientific/Engineering
Classifier: Topic :: Scientific/Engineering :: Astronomy
Classifier: Topic :: Scientific/Engineering :: Physics
Classifier: Operating System :: POSIX
Classifier: Operating System :: Unix
Classifier: Operating System :: MacOS
Classifier: License :: OSI Approved :: BSD License
Requires-Dist: confluent-kafka (>=0.11.5)
